{
    "prepare_queue": {
        "installed": [],
        "uninstalled": []
    },
    "config_munge": {
        "files": {
            "config.xml": {
                "parents": {
                    "/*": [
                        {
                            "xml": "<feature name=\"PushPlugin\"><param name=\"ios-package\" value=\"PushPlugin\" /></feature>",
                            "count": 1
                        }
                    ]
                }
            }
        }
    },
    "installed_plugins": {
        "cordova-plugin-whitelist": {
            "PACKAGE_NAME": "co.peetch.peetchApp"
        },
        "com.phonegap.plugins.PushPlugin": {
            "PACKAGE_NAME": "co.peetch.peetchApp"
        }
    },
    "dependent_plugins": {}
}